aymakan/Client.py
aymakan/__init__.py
aymakan_sdk-1.1.3.dist-info/LICENSE.txt
aymakan_sdk-1.1.3.dist-info/METADATA
aymakan_sdk-1.1.3.dist-info/WHEEL
aymakan_sdk-1.1.3.dist-info/top_level.txt
aymakan_sdk-1.1.3.dist-info/RECORD
